MobilePASSER-1.0.dist-info/DESCRIPTION.rst
MobilePASSER-1.0.dist-info/METADATA
MobilePASSER-1.0.dist-info/RECORD
MobilePASSER-1.0.dist-info/WHEEL
MobilePASSER-1.0.dist-info/entry_points.txt
MobilePASSER-1.0.dist-info/metadata.json
MobilePASSER-1.0.dist-info/top_level.txt
mobilepasser/__init__.py
mobilepasser/mobilepasser.py
mobilepasser/utils/__init__.py
mobilepasser/utils/activation_code.py
mobilepasser/utils/activation_payload_v1.py
mobilepasser/utils/base32.py
mobilepasser/utils/base32_checksum.py
mobilepasser/utils/token_generation.py
