Metadata-Version: 2.0
Name: MobilePASSER
Version: 1.0
Summary: A reimplementation of the MobilePASS client in Python.
Home-page: UNKNOWN
Author: UNKNOWN
Author-email: UNKNOWN
License: UNKNOWN
Platform: UNKNOWN
Requires-Dist: bitstring (==3.1.4)
